odoo10_addon_stock_no_negative-10.0.2.0.0-py3.8-nspkg.pth
odoo/addons/stock_no_negative/README.rst
odoo/addons/stock_no_negative/__init__.py
odoo/addons/stock_no_negative/__manifest__.py
odoo/addons/stock_no_negative/i18n/ca.po
odoo/addons/stock_no_negative/i18n/es.po
odoo/addons/stock_no_negative/i18n/fr.po
odoo/addons/stock_no_negative/i18n/hr.po
odoo/addons/stock_no_negative/i18n/nl_NL.po
odoo/addons/stock_no_negative/i18n/pt.po
odoo/addons/stock_no_negative/i18n/stock_no_negative.pot
odoo/addons/stock_no_negative/models/__init__.py
odoo/addons/stock_no_negative/models/product.py
odoo/addons/stock_no_negative/models/stock_location.py
odoo/addons/stock_no_negative/models/stock_quant.py
odoo/addons/stock_no_negative/static/description/icon.png
odoo/addons/stock_no_negative/tests/__init__.py
odoo/addons/stock_no_negative/tests/test_stock_no_negative.py
odoo/addons/stock_no_negative/views/product.xml
odoo/addons/stock_no_negative/views/stock_location.xml
odoo10_addon_stock_no_negative-10.0.2.0.0.dist-info/METADATA
odoo10_addon_stock_no_negative-10.0.2.0.0.dist-info/WHEEL
odoo10_addon_stock_no_negative-10.0.2.0.0.dist-info/namespace_packages.txt
odoo10_addon_stock_no_negative-10.0.2.0.0.dist-info/top_level.txt
odoo10_addon_stock_no_negative-10.0.2.0.0.dist-info/RECORD
